MANIFEST.in
README.md
setup.py
catalogbuilder.egg-info/PKG-INFO
catalogbuilder.egg-info/SOURCES.txt
catalogbuilder.egg-info/dependency_links.txt
catalogbuilder.egg-info/top_level.txt
cats/__init__.py
intakebuilder/CSVwriter.py
intakebuilder/__init__.py
intakebuilder/builderconfig.py
intakebuilder/catalogcols.py
intakebuilder/getinfo.py
intakebuilder/gfdlcrawler.py
intakebuilder/localcrawler.py
intakebuilder/s3crawler.py
scripts/__init__.py
scripts/gen_intake_gfdl.py
scripts/gen_intake_local.py
scripts/gen_intake_s3.py
tests/__init__.py
tests/make_sample_data.py
tests/subdirs.py
tests/test_catalog.py
tests/test_ci_dynamic.py
tests/test_import.py