Metadata-Version: 2.1
Name: catalogbuilder
Version: 2.0.1
Summary: intake-esm Catalog Generation Utilities
License: Creative Commons Attribution-Noncommercial-Share Alike license
